{
  "118169453": {
    "name": "UNO Bot",
    "history": [
      "unobot"
    ]
  },
  "146680227": {
    "name": "𝙥𝙖𝙣𝙜𝙚𝙧𝙖𝙣 𝙡𝙞𝙤𝙣",
    "history": [
      "MyLifeNull"
    ]
  },
  "178220800": {
    "name": "Spam Info Bot",
    "history": [
      "SpamBot"
    ]
  },
  "250441530": {
    "name": "⚚ 𝐕𝐄𝐑𝐀 ⍭ ⌬卐 (𝘿' 𝙇𝙪𝙘𝙖̀) #4Tos 𝟗%",
    "history": [
      "Lveraaaaa"
    ]
  },
  "260566685": {
    "name": "Channel Help",
    "history": []
  },
  "300860929": {
    "name": "SangMata",
    "history": [
      "SangMata_BOT"
    ]
  },
  "609517172": {
    "name": "Rose",
    "history": [
      "MissRose_bot"
    ]
  },
  "624384738": {
    "name": "𝟔𝟔〔𝐅𝐋〕ZEZELUCK #Jenny🏅乂 𝐙𝐄𝐍𝐈𝐓𝐇",
    "history": []
  },
  "696267355": {
    "name": "Protectron",
    "history": [
      "ProtectronBot"
    ]
  },
  "749687321": {
    "name": "↻ DIGI ANTI ⇦",
    "history": [
      "digi9bot"
    ]
  },
  "774355494": {
    "name": "↻ DIGI ANTI ⇦",
    "history": [
      "digi6bot"
    ]
  },
  "890581021": {
    "name": "Group Help",
    "history": [
      "GHClone1Bot"
    ]
  },
  "972676565": {
    "name": "⸸𝒙𝒗𝒂𝒏𝒆𝒔𝒄𝒕 𝒐𝒍𝒊𝒏𝒏 𝒇𝒐𝒓𝟐𝒕",
    "history": [
      "oIinnckep"
    ]
  },
  "1001159887": {
    "name": "🌞⃟ᴠͥɪͣᴘͫ Q𝞄ֵ𝝴۪𝝴۪𝗻ׁ A𝗹𝘆𝝰ׄ ⺏ 𝐌𝐎𝐎𝐍𝐋𝐈𝐆𝐇𝐓 ⺏",
    "history": [
      "AlyaChans"
    ]
  },
  "1072730592": {
    "name": "𝗠𝗔𝗥𝗫𝗫 𝗢𝗙𝗙𝗜𝗖𝗜𝗔𝗟𝗟#𝟒𝐓𝐎𝐒 & 𝐓𝟓",
    "history": [
      "MarxxxOfficialll"
    ]
  },
  "1102295941": {
    "name": "?",
    "history": [
      "SiapaYaa152"
    ]
  },
  "1105039063": {
    "name": "𝙏𝙪𝙖𝙣 𝙈𝙪𝙙𝙖 𝘾𝙤𝙗𝙧𝙖",
    "history": []
  },
  "1132106880": {
    "name": "Seraa ₍ᐢ. .ᐢ₎♡",
    "history": [
      "Kawaisera"
    ]
  },
  "1140963841": {
    "name": "Support Monzo Bangking",
    "history": []
  },
  "1151695008": {
    "name": "—! 𝐕𝐧𝐗 ALIN 𝐓𝟓",
    "history": []
  },
  "1198139254": {
    "name": "imortlado",
    "history": []
  },
  "1273649186": {
    "name": "𝖝𝖊𝖑𝖑𝖝?",
    "history": [
      "BackupDhrzx"
    ]
  },
  "1295080722": {
    "name": "[BACK]",
    "history": []
  },
  "1322117716": {
    "name": "ottooo ─ x !!",
    "history": []
  },
  "1328894777": {
    "name": "￴ ￴ ￴ ￴ ￴￴ramz honrado",
    "history": []
  },
  "1337033875": {
    "name": "[𝗔𝟳𝟲]",
    "history": [
      "GwVsmakloee"
    ]
  },
  "1341370908": {
    "name": "𝑩𝒊𝒏 𝒇𝒐𝒓𝒕𝒘𝒚𝒏𝒕𝒚",
    "history": []
  },
  "1382726693": {
    "name": "⋆ GyzêñLyōráã`+..",
    "history": [
      "GyzenLoww"
    ]
  },
  "1402174935": {
    "name": "𝐒𝐚𝐱𝐱ā 𝐓𝟓",
    "history": [
      "sakanyabobo"
    ]
  },
  "1406430377": {
    "name": "୨୧ 𝑨𝒖𝒓𝒆𝒍𝒊𝒂 𝑵𝒚𝒙𝒂 ˚₊ੈ‧₊˚",
    "history": []
  },
  "1409815531": {
    "name": "D.Ends",
    "history": []
  },
  "1458955929": {
    "name": "⏤͟͟͞Xyroo ᥫ᭡",
    "history": [
      "ynzxxstr"
    ]
  },
  "1478220118": {
    "name": "#1 𝗥𝗮𝗿𝗮 𝗬𝗼𝗛𝗶𝗸𝗮𝘁𝘀𝗵𝘂 益",
    "history": []
  },
  "1478372837": {
    "name": "⏤͟͟͞͞𝑴𝒂𝒉𝒆𝒔𝒂 𝒇𝒐𝒓𝒕𝒘𝒚𝒏𝒕𝒚",
    "history": []
  },
  "1478839005": {
    "name": "./ârga #Màou",
    "history": [
      "argaXoficialll"
    ]
  },
  "1486198121": {
    "name": "𝐙𝐢𝐧𝐧 𝙷𝚊𝚗𝚍𝚜𝚘𝚖𝚎 𝖋𝖙 𝗫͢𝘅𝗫 𝘾𝙖𝙨𝙩𝙚𝙡𝙡𝙤`",
    "history": [
      "NEWERAAZS"
    ]
  },
  "1531911636": {
    "name": "⏤͟͟͞͞𝙽𝙲 ynzxx || 1970 🄿🄰🄻🅂🅄",
    "history": []
  },
  "1541352334": {
    "name": "TsutomuShimomura",
    "history": []
  },
  "1550149627": {
    "name": "𝙲𝚓♰ (fokus rl)",
    "history": [
      "norctcj"
    ]
  },
  "1576834717": {
    "name": "『愛𝐅𝟏』𝙾𝙽𝙻𝚈`𝐆𝐈𝐊𝐒",
    "history": [
      "GIKSPINTER"
    ]
  },
  "1581765458": {
    "name": "헐 𝗗𝗭𝗔𝗞𝗞𝗬 ›",
    "history": [
      "dzakkyoffc"
    ]
  },
  "1614435276": {
    "name": "Z o r d",
    "history": [
      "YatimSoker"
    ]
  },
  "1626555135": {
    "name": "χλz ζεpyšk",
    "history": []
  },
  "1637638124": {
    "name": "𝖬𝗂𝖺 𝖮𝖿𝖿𝗂𝖼𝗂𝖺𝗅 [ 𝖺𝗅𝗅 𝗍𝗋𝗑 𝗈𝗉𝖾𝗇 ]",
    "history": []
  },
  "1638112364": {
    "name": "ᯓ𝗞𝗶𝗻𝗴𝗭𝘆𝗼𝗻 𝘿' 𝙇𝙪𝙘𝙖̀ 𓇢𓆸",
    "history": []
  },
  "1644843151": {
    "name": "𝗟𝗼𝘅𝘅𝘆",
    "history": [
      "loxxynabboo"
    ]
  },
  "1654916541": {
    "name": "Barker tag bot 2",
    "history": [
      "ZazyvalaTag2Bot"
    ]
  },
  "1663207738": {
    "name": "⏤͟͟͞͞L̷E̷K̷Z̷O̷ 𝙲𝙸𝚃𝙴𝙽𝟽",
    "history": [
      "LekzoMarketV22"
    ]
  },
  "1678079467": {
    "name": "𝐑𝐚𝐡𝐦𝐚𝐧 𝐗 𝐀𝐩𝐤 𝐁𝐮𝐠",
    "history": []
  },
  "1697095360": {
    "name": "acaall",
    "history": []
  },
  "1718367827": {
    "name": "友 𝙎𝘼𝙆𝘼𝙏𝘼 ´ཀ`",
    "history": [
      "sakata_real"
    ]
  },
  "1745417294": {
    "name": "⏤͟͟͞͞𝐏𝐑𝐈𝐒𝐌𝐀𝐓𝐈𝐂 ☇ #𝟒𝐓𝐨𝐬 ⍭",
    "history": []
  },
  "1768150966": {
    "name": "メ𝙇𝙀𝙊𝙊` 𝒇𝒐𝒓𝒕𝒘𝒚𝒏𝒕𝒚 🇦🇱",
    "history": [
      "LEOOFACK"
    ]
  },
  "1793352182": {
    "name": "TikArchive | TikTok Downloader",
    "history": [
      "tikloadtokbot"
    ]
  },
  "1799802763": {
    "name": "./NityXIrena ( OPEN PARTNER 3K ) X 𝐓𝟓",
    "history": [
      "NityWasNew"
    ]
  },
  "1819961687": {
    "name": "⌕ 𝑷𝒆𝒕𝒊𝒏𝒈𝒈𝒊 | 𝐍𝐇",
    "history": []
  },
  "1820341629": {
    "name": "𝗩𝗼𝗿𝗶𝘂𝘀𝟴𝟴𝟴",
    "history": []
  },
  "1827204836": {
    "name": "—͟͞͞𝗗𝗲𝗹𝗽𝗶𝗻𝗪𝗵𝗮𝘁𝘀𝗔𝗽𝗽",
    "history": []
  },
  "1832166032": {
    "name": "YANZ OFFICIAL (akun ke 2)",
    "history": []
  },
  "1868673737": {
    "name": "yàn #immortalBoys !",
    "history": []
  },
  "1872202016": {
    "name": "『 𝘿𝙞𝙠𝙖_𝙢𝙙 𝙉𝙞𝙚 × 𝙊𝙋𝙀𝙉 𝘼𝙋𝙆 𝙍𝘼𝙄𝘿𝙀𝙉 』🫍",
    "history": []
  },
  "1874284647": {
    "name": "little girl cyutii",
    "history": [
      "hellnaamenn"
    ]
  },
  "1876376399": {
    "name": "gerald. / › t.me/raabl",
    "history": [
      "geraalb"
    ]
  },
  "1886616400": {
    "name": "── Ƈêpσтχz Öffiƈiαl",
    "history": []
  },
  "1900138619": {
    "name": "𝐕𝐞𝐧𝙩𝐞𝐥𝐚#immortal 合🏅",
    "history": [
      "Yatimbegok"
    ]
  },
  "1947655995": {
    "name": "the fvck off",
    "history": []
  },
  "1956929425": {
    "name": "dikz",
    "history": []
  },
  "2014533376": {
    "name": "𝒆𝒌𝒊𝒌𝒌 𝒇𝒐𝒓𝒕𝒘𝒚𝒏𝒕𝒚?",
    "history": [
      "ekikaja"
    ]
  },
  "2031838261": {
    "name": "Support Monzo Banking Service",
    "history": [
      "ytimfuc"
    ]
  },
  "2045375485": {
    "name": "•AZF•",
    "history": []
  },
  "2069532673": {
    "name": "⏤<⌬> 𝑨𝒍𝒆𝒙𝒂𝒏𝒅𝒆𝒓 ϟ 𝑿𝒂𝒗𝒊𝒆𝒓",
    "history": []
  },
  "2086517669": {
    "name": "Tuan YanXzOffc",
    "history": []
  },
  "2093510200": {
    "name": "(っ◔◡◔)っ mellstecuu ♥",
    "history": [
      "mellstecuu"
    ]
  },
  "2131787866": {
    "name": "🦠⃟ᴠͥɪͣᴘͫ 𝑽𝑰𝑵𝒁☚",
    "history": [
      "DlyKcungDkVINZ"
    ]
  },
  "3120756054": {
    "name": "",
    "history": [
      "ynzxxstur"
    ]
  },
  "3206831098": {
    "name": "",
    "history": [
      "areashare_sc"
    ]
  },
  "3367675759": {
    "name": "",
    "history": [
      "allinfo252"
    ]
  },
  "3528603329": {
    "name": "",
    "history": [
      "fixredfufu"
    ]
  },
  "3618195526": {
    "name": "",
    "history": [
      "lanzoffiiciall"
    ]
  },
  "3639149685": {
    "name": "",
    "history": [
      "beyourslin"
    ]
  },
  "3700172754": {
    "name": "",
    "history": [
      "ziyyXstoree"
    ]
  },
  "3713466558": {
    "name": "",
    "history": [
      "maklobautnah"
    ]
  },
  "3719597662": {
    "name": "",
    "history": [
      "merchantlabel"
    ]
  },
  "3772763230": {
    "name": "",
    "history": [
      "testiIangzx"
    ]
  },
  "3841407767": {
    "name": "",
    "history": []
  },
  "3842131835": {
    "name": "",
    "history": [
      "bottirzz"
    ]
  },
  "3946517336": {
    "name": "",
    "history": [
      "olinnmwah"
    ]
  },
  "4281458690": {
    "name": "",
    "history": [
      "aditneedbuyer"
    ]
  },
  "8348079884": {
    "name": "nall",
    "history": [
      "rexx_yoo"
    ]
  },
  "8493158139": {
    "name": "──𝘈𝘯𝘥𝘳𝘪",
    "history": []
  },
  "8509643161": {
    "name": "𝐄𝐕𝐑 - Naruya Market OFC ||",
    "history": [
      "Narayuizumi"
    ]
  },
  "7839922490": {
    "name": "𝐰𝐧𝐳𝐲𝐲𝐨𝐱𝐲𝟔𓆰 [ rarely on ]",
    "history": []
  },
  "8952276834": {
    "name": "Fahmi",
    "history": [
      "FahmiGs"
    ]
  },
  "7948982552": {
    "name": "ㅤkarl",
    "history": [
      "crruality"
    ]
  },
  "8656440915": {
    "name": "𝖾𝗅𝗂𝗈𝗈",
    "history": []
  },
  "8719842270": {
    "name": "BOT BUILD WEB2APK PANZ",
    "history": [
      "buildapkpanzxx_bot"
    ]
  },
  "7811327470": {
    "name": "𝗔𝗧𝗘𝗟𝙢𝙪𝙨𝙞𝙘",
    "history": [
      "ATELmusicbot"
    ]
  },
  "8855744386": {
    "name": "Vanzz",
    "history": [
      "VANZZTEAM"
    ]
  },
  "8988466456": {
    "name": "𝐄𝐕𝐑 Ikyyy #ImmortalBoys !",
    "history": [
      "saselos"
    ]
  },
  "8686617824": {
    "name": "Afgan",
    "history": []
  },
  "7895956581": {
    "name": "van",
    "history": [
      "Vansajah"
    ]
  },
  "5512285512": {
    "name": "ϟ 𝐙𝐋𝐃『 𝐊𝐄𝐍𝐙 𝐈𝐒 𝐇𝐄𝐑𝐄 』﷽(⩇⩇:⩇⩇)",
    "history": [
      "Kenzishare4you"
    ]
  },
  "8652439449": {
    "name": "Death 🆘",
    "history": [
      "RuiVortex"
    ]
  },
  "8341876561": {
    "name": "⚡ᯓ 𝙍𝙚𝙣𝙓𝙞𝙓𝙭 #Mørtìs 益 (⩇⩇:⩇⩇)",
    "history": []
  },
  "8079897719": {
    "name": "ᯓ[𝙻𝚇𝙰 𝚃𝙴𝙰𝙼] Anxy.dart 𒄆",
    "history": [
      "Unknownpipp"
    ]
  },
  "8621743724": {
    "name": "𝘈𝘻𝘻 𝘹𝘦𝘷𝘯",
    "history": [
      "Clickplerrr"
    ]
  },
  "8549158538": {
    "name": "𝗫𝗶𝗲安加𝐓𝟓 ⁶🤷⁷",
    "history": [
      "maklowhxh"
    ]
  },
  "8336976292": {
    "name": "👻Lanzz👻𝘿' 𝙇𝙪𝙘𝙖̀ 𓇢𓆸",
    "history": [
      "LanzzzzID"
    ]
  },
  "8892371615": {
    "name": "⏤͟͟𝐗𝐭𝐞⃟𝐜🦠⃟𝐆𝐍𝐓𝐆767 x̸♛⃝🦋⃟ᴠͥɪͣᴘͫ 𓆩⚝𓆪",
    "history": [
      "JoliaValeria"
    ]
  },
  "7282233496": {
    "name": "‍ ᅠ ︎ ︎ ︎ ︎ ᅠ ︎ ︎ ︎ ︎",
    "history": [
      "toIoIuu"
    ]
  },
  "8743236358": {
    "name": "𝘟𝘺𝘷𝘦𝘭𝘦𝘯𝘵𝘴 Noxx 👑🔥",
    "history": [
      "Noxx4Malas"
    ]
  },
  "8522905377": {
    "name": "—_𝐎𝐓 ⚡︎ 𝐀𝐋𝐃𝐈𝐙𝐙 𝐂𝐄𝐎 ♞",
    "history": [
      "aldiprojet"
    ]
  },
  "7836077330": {
    "name": "𝐁𝐢𝐦𝐳𝐔𝐧𝐜𝐢𝐧𝐡𝐚 𝐓𝟓",
    "history": []
  },
  "7257443662": {
    "name": "ɪ'ᴍ ϟ ɴᴜxᴄᴋ • Back?",
    "history": []
  },
  "8633682712": {
    "name": "Mario Builder app ©",
    "history": [
      "BuilderappRaszbot"
    ]
  },
  "8555758308": {
    "name": "mbutlah",
    "history": [
      "cowoqlu"
    ]
  },
  "8677609629": {
    "name": "Vilo Cpanel",
    "history": [
      "ViloCpanelBot"
    ]
  },
  "7731848894": {
    "name": "kent store",
    "history": []
  },
  "8181994424": {
    "name": "Joe🐾",
    "history": []
  },
  "8751381551": {
    "name": "𝒃𝒐𝒕 𝒌𝒚𝒓𝒐 𝒎𝒅 V4",
    "history": [
      "kyromd_bot"
    ]
  },
  "8706227391": {
    "name": "dilz",
    "history": []
  },
  "8352293246": {
    "name": "ᯓ卐 ⏤͟͟𝐕𝐢𝐧𝐳𝐂𝐡𝐲 乂┃𝐓𝟓 シ 𝐃𝐞𝐯 𓂀",
    "history": [
      "vinzyapping"
    ]
  },
  "8283128898": {
    "name": "Santai?",
    "history": [
      "Fianz8"
    ]
  },
  "8671216916": {
    "name": "Ray Akyzén",
    "history": [
      "RayAkyzen"
    ]
  },
  "8493709743": {
    "name": "𝐑𝐌𝐙𝐙. ㅣAPP PREM • PANEL LEGAL",
    "history": []
  },
  "8755668234": {
    "name": "Support Line Bank Service Care",
    "history": [
      "LineBank_Official_Service_Carex1"
    ]
  },
  "7711635642": {
    "name": "b4ýzxc.",
    "history": []
  },
  "5568014048": {
    "name": "Barker tag bot 7",
    "history": [
      "ZazyvalaTag7Bot"
    ]
  },
  "6717611846": {
    "name": "𝙔𝘼𝙉𝙕 𝙲𝙸𝚃𝙴𝙽𝟽#VESTRIK 𝘿' 𝙇𝙪𝙘𝙖̀ 𓇢𓆸🥀",
    "history": []
  },
  "8289265556": {
    "name": "Lucíus #Arzov",
    "history": [
      "SetyaLagiBobo"
    ]
  },
  "8760312924": {
    "name": "𝐀𝐆𝐈𝐈 𝐓𝟓🇦🇱",
    "history": []
  },
  "8749993860": {
    "name": "⏤͟͟͞͞RilzZ° 𝘿' 𝙇𝙪𝙘𝙖̀ 𓇢𓆸",
    "history": []
  },
  "8940427427": {
    "name": "𝐷𝑒𝑝𝑝𝑒𝑋",
    "history": []
  },
  "8234628386": {
    "name": "𝗫𝗶𝗲 — 𝙒𝙞𝙯𝙯𝙆𝙖𝙜𝙚𝙣𝙤𝙪",
    "history": [
      "WizZzXTzy1"
    ]
  },
  "8644628519": {
    "name": "Alexander",
    "history": [
      "Streeking_Sevennight"
    ]
  },
  "8860531866": {
    "name": "Unsupported characters",
    "history": []
  },
  "7853377721": {
    "name": "celsi",
    "history": [
      "clseaaoeel"
    ]
  },
  "7427790244": {
    "name": "AzkarCuy Share",
    "history": []
  },
  "8346030693": {
    "name": "𝚈𝚄𝙲𝙰𝙽𝙽 𝙼𝙳",
    "history": [
      "yucannnmdbot"
    ]
  },
  "7988909500": {
    "name": "𝑩𝑶𝑻 𝑱𝑨𝑺𝑬𝑩 𝑷𝑹𝑬𝑴𝑰𝑼𝑴 𝑳𝑼𝑻𝑷𝑬𝑿𝒁 𝑶𝑭𝑭𝑰𝑪𝑰𝑨𝑳",
    "history": [
      "jasebpexz_bot"
    ]
  },
  "8492021451": {
    "name": "𝑹𝒂𝑭𝒛 [𝑶𝒑𝒆𝒏 𝒎𝒖𝒓𝒃𝒖𝒈 ξ 𝒕𝒗𝒆]",
    "history": []
  },
  "8793788537": {
    "name": "NΛRΣПDЯΛZYYRΣΛL6X",
    "history": [
      "NarendrazyyReal"
    ]
  },
  "8962327151": {
    "name": "WHO IM XD #immortal",
    "history": []
  },
  "7423827025": {
    "name": "ALBRIQ",
    "history": []
  },
  "7605597547": {
    "name": "𝐓𝐡𝐞 𝐖𝐢𝐧𝐧𝐞𝐫𝐬",
    "history": []
  },
  "8542493049": {
    "name": "©Låñgzz || Ö££ï¢ïål",
    "history": [
      "Langzz31xx"
    ]
  },
  "8390546115": {
    "name": "Angkasa Bot Multi Device [ V9 ]",
    "history": [
      "angkasamdbot"
    ]
  },
  "8295571870": {
    "name": "梅琳達·林🎀",
    "history": []
  },
  "7871673904": {
    "name": "ADMIN STEVEN",
    "history": [
      "SteveNnnReaaL"
    ]
  },
  "8519603685": {
    "name": "Kaiii",
    "history": []
  },
  "5705401731": {
    "name": "All || 抗头孢菌素",
    "history": []
  },
  "8448734242": {
    "name": "JB ALL GAME CEK BIO",
    "history": []
  },
  "8895773076": {
    "name": "ham",
    "history": [
      "hamznokos"
    ]
  },
  "5559751246": {
    "name": "𝗮𝗯𝗱𝘆",
    "history": []
  },
  "8331533515": {
    "name": "Support Monza Banking 𝗦𝗲𝗿𝘃𝗶𝗰𝗲",
    "history": [
      "MonzoSupportBank11"
    ]
  },
  "8468563928": {
    "name": "𝙈𝙃𝙈𝙈𝘿.𝙏𝙈𝙈𝘼[𝙁𝘼𝙎𝙏𝙍𝙀𝙎𝙋𝙋]",
    "history": []
  },
  "8798823291": {
    "name": "MLO | BOT",
    "history": [
      "myloveotp_bot"
    ]
  },
  "8272641213": {
    "name": "Nicholaus.",
    "history": []
  },
  "7821963818": {
    "name": "komeng",
    "history": []
  },
  "8728798273": {
    "name": "Official_CoinMarketCap_Serviceb3",
    "history": []
  },
  "8906944068": {
    "name": "SUPPORT BLACKROCK",
    "history": [
      "Official_BlackRock_official"
    ]
  },
  "8055151130": {
    "name": "ʙᴀʀʀɴᴏᴛᴅᴇᴠ",
    "history": [
      "barrnodev"
    ]
  },
  "8213518197": {
    "name": "Farhan",
    "history": []
  },
  "8818449316": {
    "name": "Bot cpanel",
    "history": [
      "Botpanelajay_bot"
    ]
  },
  "8566805074": {
    "name": "Jasa beli/jual WhatsApp OTP 服务",
    "history": []
  },
  "6530457902": {
    "name": "Support Monzo Banking Service",
    "history": [
      "OfficiaI_Monzo_Support_Banking9"
    ]
  },
  "5566538214": {
    "name": "BranzzPedia #jenny",
    "history": []
  },
  "8436763781": {
    "name": "𝙇𝙀𝙊𝙓𝙔𝙕",
    "history": [
      "Leoxyzofficial"
    ]
  },
  "4429142600": {
    "name": "",
    "history": [
      "voidengineinfo"
    ]
  },
  "8913462371": {
    "name": "zayn",
    "history": []
  },
  "8613490105": {
    "name": "HanZzXdd",
    "history": [
      "HanZzXdd71"
    ]
  },
  "8796369623": {
    "name": "𝐑𝐀𝐉𝐀 𝐈𝐁𝐋𝐈𝐒 𝐎𝐏𝐄𝐍 𝐁𝐔𝐀𝐓 𝐀𝐏𝐊 ♛",
    "history": []
  },
  "8231333199": {
    "name": "L⁴ —◗ Dikaa o𝖿𝖿𝗂𝖼𝗂𝖺𝗅",
    "history": []
  },
  "5902801752": {
    "name": "ᴅɪʟxʏᴢ",
    "history": [
      "ytimluu"
    ]
  },
  "8747609337": {
    "name": "Jelool",
    "history": [
      "Jeloolofficial"
    ]
  },
  "7902328386": {
    "name": "『𝙲𝙴𝙾』Sul 4u",
    "history": []
  },
  "4403493534": {
    "name": "",
    "history": [
      "alltestiazz19"
    ]
  },
  "8632159676": {
    "name": "YNX CRASH",
    "history": [
      "DataBaseVoxyCrash_bot"
    ]
  },
  "8097112220": {
    "name": "- ⏤͟͟͞͞𝐖𝐈𝐍𝐙ˣ support",
    "history": []
  },
  "6742560069": {
    "name": "𝐄𝐕𝐑 𝑹𝒊𝒓𝒊𝒏 #𝑪𝒆𝒍𝒆𝒔𝒕𝒊𝒂",
    "history": [
      "momykamu"
    ]
  },
  "8826761304": {
    "name": "𝖬𝖽𝖴𝗇𝖽𝖾𝗋𝖲𝖺𝗅𝖾 𝖬𝗎𝗅𝗍𝗂 𝖣𝖾𝗏𝗂𝖼𝖾 𝖡𝗈𝗍",
    "history": [
      "MdUnderSale_Bot"
    ]
  },
  "8708481777": {
    "name": "ᯓ𝙏𝙧𝙞𝙯𝙭✘ 𝘿' 𝙇𝙪𝙘𝙖̀𓇢𓆸",
    "history": [
      "TrizxNotDev"
    ]
  },
  "6961897836": {
    "name": "FOLLOWERS MURAH",
    "history": []
  },
  "8706034579": {
    "name": "BOT MD BY PANJI",
    "history": [
      "BOTMDBYPANJIBOT"
    ]
  },
  "7635116350": {
    "name": "𝐍𝐚𝐭𝐱𝐎𝐟𝐟𝐢𝐜𝐢𝐚𝐥 卐 the gherial 𝐆𝐋𝐗 [ OPEN REKBER MC ] ۞👮",
    "history": [
      "natxtzy_lagibobok"
    ]
  },
  "8424097898": {
    "name": "💥>!! NOT DEV MOTUZ !!<💥",
    "history": [
      "VANZZ_project"
    ]
  },
  "8240543049": {
    "name": "𝙐𝙉𝙕 [𝗧𝗔𝗠𝗨𝗭]",
    "history": [
      "unzzstecu"
    ]
  },
  "8100553664": {
    "name": "RINZ",
    "history": []
  },
  "8975837723": {
    "name": "Multi Device Arlend",
    "history": [
      "mdarlendbot"
    ]
  },
  "8248022180": {
    "name": "About [A76] RYU 🥵",
    "history": []
  },
  "8088569770": {
    "name": "Kunyuk",
    "history": []
  },
  "7848723736": {
    "name": "𝘽𝙖𝙖𝙣",
    "history": []
  },
  "8419076768": {
    "name": "𝐋𝐮́𝐜𝐚́𝐬 #𝐈𝐌𝐌❂𝐑𝐓𝐀𝐋🥇",
    "history": [
      "maklumati1"
    ]
  },
  "7687928713": {
    "name": "XDitz 𝐓𝟓 🎖",
    "history": []
  },
  "5593976615": {
    "name": "˹ᴛᴄʜ ᴍᴜsɪᴄ ʙᴏᴛ♪˼",
    "history": [
      "TchMusicBot"
    ]
  },
  "8624189189": {
    "name": "Dreckz777",
    "history": []
  },
  "8675972458": {
    "name": "©️ 𝗫𝗜𝗘 - 𝗔𝗟𝗩𝗔𝗥𝗢 </> 𝗫𝗬𝗭",
    "history": [
      "Alvaro_102"
    ]
  },
  "8584295347": {
    "name": "Dxxxx",
    "history": []
  },
  "8474065755": {
    "name": "Support Line Bank Service Care",
    "history": []
  },
  "7983894285": {
    "name": "RAAXD HOST",
    "history": []
  },
  "8686921481": {
    "name": "⏤͟͟͞𝗩𝙖𝙣𝙯 𝘿' 𝙇𝙪𝙘𝙖̀ 𓇢𓆸",
    "history": []
  },
  "8863773375": {
    "name": "API APK BUG",
    "history": [
      "Xorz_her_bot"
    ]
  },
  "7549246394": {
    "name": "༒︎⏤͟͟͞𝙇𝙪𝙢𝙞𝙣𝙚𝙧𝙚༒︎",
    "history": []
  },
  "8707720587": {
    "name": "Unknown",
    "history": []
  },
  "8845722879": {
    "name": "Wann",
    "history": [
      "kutangrombeng"
    ]
  },
  "8652311138": {
    "name": "[𝗔𝟳𝟲]",
    "history": []
  },
  "8927583550": {
    "name": "Support Monzo Banking Service",
    "history": []
  },
  "5695704677": {
    "name": "Tag All Bot",
    "history": [
      "TagALLBot_Bot"
    ]
  },
  "7335689814": {
    "name": "ZeꭈׁׅoTzׁׅ֬y",
    "history": [
      "ZeroPribb"
    ]
  },
  "8075050310": {
    "name": "𝙍𝙤𝙯𝙜𝙚𝙧𝙯𝙓",
    "history": []
  },
  "6914727695": {
    "name": "𝐄𝐕𝐑 | 𝗔𝘀𝗮 𝗘𝗮𝗹𝗶𝘇𝗮𝗯𝗲𝘁𝗵 𝐓𝟓",
    "history": [
      "maklowhy"
    ]
  },
  "6527494952": {
    "name": "—𝐑𝐚𝐧𝐳𝐗 𝐄𝐦𝐩𝐢𝐫𝐞 † 𝐅𝐋",
    "history": [
      "F4ckMaklowh"
    ]
  },
  "6863258183": {
    "name": "⛦⁪⁬⁮⁮𝐑𝐞́𝐲𝐧𝐚𝐫𝐝 𝐇𝐚́𝐧𝐝𝐬𝐨𝐦𝐞`",
    "history": [
      "clickusername2"
    ]
  },
  "7719556109": {
    "name": "𝐓𝐚́𝐧𝐧𝐳𝐲 卐 𝐋𖥕𝐓𝐔𝐒🧸",
    "history": [
      "maklohkeceh"
    ]
  },
  "5556127397": {
    "name": "VANZ OFICIAL 2",
    "history": []
  },
  "8939948649": {
    "name": "Fahri",
    "history": []
  },
  "7059136099": {
    "name": "NoahhZx",
    "history": []
  },
  "7801563147": {
    "name": "LangzzNotdevv 😶‍🌫️",
    "history": []
  },
  "8593481078": {
    "name": "Zxv",
    "history": [
      "CXCY24566556"
    ]
  },
  "8934003678": {
    "name": "𝐉𝐄𝐍𝐙𝐙 𝐎𝐅𝐅𝐈𝐂𝐈𝐀𝐋",
    "history": []
  },
  "8853745867": {
    "name": "BOT BUILD ZHAHER 1",
    "history": [
      "build_zhaher_bot"
    ]
  },
  "8213470050": {
    "name": "𝗦𝗘𝗡𝗭𝗣𝗘𝗗𝗜𝗔 ( Ready Panel Pterodactly & Vps )",
    "history": []
  },
  "8512110447": {
    "name": "乂𝚠𝚊𝚝𝚏𝚘𝚛𝚍𝚍",
    "history": []
  },
  "8701434255": {
    "name": "mmey°`",
    "history": []
  },
  "6062019012": {
    "name": "aké Küs",
    "history": []
  },
  "8628025043": {
    "name": "⏤͟͟͞͞l₹ey`𝘿' 𝙇𝙪𝙘𝙖̀ 𓇢𓆸",
    "history": []
  },
  "8676051659": {
    "name": "𝘽𝙊𝙏",
    "history": [
      "RyuuXyz_bot"
    ]
  },
  "7489437401": {
    "name": "𝔻𝕒𝕣𝕜𝕜 𝕤𝕚𝕤𝕥𝕖𝕞",
    "history": []
  },
  "8039559687": {
    "name": "zansshopp",
    "history": []
  },
  "8999196155": {
    "name": "Starboy Fan",
    "history": []
  },
  "8721655019": {
    "name": "ᯓ𝒛𝟏𝒚𝒂𝒅𝟏𝟕!4Tos",
    "history": [
      "sig4ntenk"
    ]
  },
  "7969108466": {
    "name": "ー𝑩𝒓𝒁 𝑽𝒂𝒍𝒌𝒉𝒊𝒆𝒓.",
    "history": []
  },
  "8272267454": {
    "name": "ZUL",
    "history": []
  },
  "8642041248": {
    "name": "ᯓ 𝑱𝑬𝑳𝑳𝒀. 𝘿' 𝙇𝙪𝙘𝙖̀ 𓇢𓆸",
    "history": []
  },
  "8677606708": {
    "name": "BOT CPANEL",
    "history": [
      "cpanelsanzoffc_bot"
    ]
  },
  "7351443961": {
    "name": "𒈔𝙍𝙄𝙉𝙕𝙕 𝙏𝙕𝙔𖠄",
    "history": []
  },
  "8604069421": {
    "name": "CoinMarketCap Support Service",
    "history": []
  },
  "8172450352": {
    "name": "` — 𝐕𝐚𝐥𝐳𝐲 𝐈𝐬 𝐇𝐞𝐫𝐞 || ⏤͟͟͞͞𝗡𝗼𝘃𝗮",
    "history": []
  },
  "5579820849": {
    "name": "⛦⁪⁬⁮⁮𝐘𝐚𝐧𝐛𝐞` [ ᴘʀᴏᴍᴏꜱɪ ]",
    "history": []
  },
  "8925872467": {
    "name": "¤‌๋‌ࣩࣩࣩࣩࣩࣩࣩࣩࣩࣩࣩࣩࣩࣩࣩࣩࣩࣩࣩࣩࣩࣩࣩࣩࣩࣧࣧࣧࣧࣧࣧࣧࣧ𝙔𝙖𝙣𝙯𝙯 𝘿' 𝙇𝙪𝙘𝙖̀ 𓇢𓆸",
    "history": []
  },
  "5203753995": {
    "name": "|| 𝐐𝐮𝐚𝐧𝐭𝐮𝐦𝐗 ( bangun ni ) صبر",
    "history": []
  },
  "8496303422": {
    "name": "CoinMarketCap Support Service",
    "history": [
      "Official_CoinMarketCap_Service44"
    ]
  },
  "7329802442": {
    "name": "ràyns",
    "history": [
      "topsnyoli"
    ]
  },
  "7054750339": {
    "name": "bijiong fyne😝",
    "history": []
  },
  "8911562388": {
    "name": "SndyNotDev_𝐄𝐕𝐑",
    "history": [
      "LIVENDOS2"
    ]
  },
  "6068994854": {
    "name": "ZYY STURR",
    "history": []
  },
  "8702091162": {
    "name": "—𝐑𝐲𝐮𝐮𝐮𝐗𝐍𝐚𝐧𝐳 |",
    "history": []
  },
  "8887348007": {
    "name": "MULTIDEVICE BOT",
    "history": [
      "multideviceditzbot"
    ]
  },
  "6932706041": {
    "name": "Kayy",
    "history": []
  },
  "8685290981": {
    "name": "𝙄'𝙈 𝙀𝙓𝙄𝙉𝙉𝙉 - 𝐗𝟕",
    "history": [
      "Exinnn13"
    ]
  },
  "8622215587": {
    "name": "umi",
    "history": []
  },
  "6264501689": {
    "name": "Uzi (fokus rl)",
    "history": []
  },
  "8903893658": {
    "name": "CPANEL X GAZ",
    "history": [
      "MELIDUNGIBot"
    ]
  },
  "8832468783": {
    "name": "˖ ֹ੭୧ 𝙤𝙡𝙞𝙣𝙚𝙚 𝒇𝒐𝒓𝒕𝒘𝒚𝒏𝒕𝒚 𝘿' 𝙇𝙪𝙘𝙖̀ 𓇢𓆸",
    "history": []
  },
  "8918706031": {
    "name": "SHIROU14 STORE",
    "history": []
  },
  "8287063097": {
    "name": "劉祖新",
    "history": []
  },
  "8307709277": {
    "name": "𝕹𝖊𝖜𝕰𝖗𝖆 𝚉𝙸𝙼𝙼𝙸𝙽𝙷𝙾 X 卐 L𖥕TUS",
    "history": []
  },
  "8659146870": {
    "name": "iky",
    "history": [
      "ikyajaweh"
    ]
  },
  "8200190115": {
    "name": "hamxyz4note T5",
    "history": []
  },
  "7755873073": {
    "name": "⏤͟͟͞͞ 𝗗𝗮𝘃𝗶𝘀 ╾╼ ✧",
    "history": []
  },
  "8495130991": {
    "name": "ARZZ OPEN 24 JAM",
    "history": []
  },
  "8298614392": {
    "name": "Vonix",
    "history": [
      "VonixTheSaa"
    ]
  },
  "8622000731": {
    "name": "AzuraX bot apps",
    "history": [
      "AzuraXXXXXXbot"
    ]
  },
  "8771779686": {
    "name": "𝗔𝘀𝗶𝘀𝘁𝗲𝗻 𝗧𝗶𝗿𝘇𝘇",
    "history": [
      "resellertirzzbot"
    ]
  },
  "8645024340": {
    "name": "AUTO ORDERR VPS",
    "history": [
      "AUTOORDERVPSAWET_bot"
    ]
  },
  "8265718776": {
    "name": "ꋊꃳ 𝙉𝙄𝙀𝙇𝙇𝙓𝙔𝙉 𝙊𝙁𝙁𝙄𝘾𝙄𝘼𝙇 🜲𝗔𝗹𝘁𝗲𝗿𝗘𝗴𝗼⛅",
    "history": []
  },
  "7919552205": {
    "name": "putra",
    "history": []
  },
  "8908621971": {
    "name": "𝙱𝙾𝚃 𝙼𝙳 𝙼𝚄𝙻𝚃𝙸 𝙿𝚄𝙽𝙶𝚂𝙸",
    "history": [
      "PrismaticMulti_Bot"
    ]
  },
  "8737264547": {
    "name": "Muis",
    "history": [
      "Muisvipp"
    ]
  },
  "8789778184": {
    "name": "#𝐓𝟓",
    "history": []
  },
  "6859340101": {
    "name": "Lanz𑲭𑲭𑲭𑲭𑲭𑲭𑲭𑲭𑲭𑲭𑲭𑲭𑲭𑲭𑲭𑲭𑲭𑲭𑲭𑲭𑲭𑲭⸙ꠋꠋꠋꠋꠋꠋꠋꠋꠋꠋꠋꠋꠋꠋꠋꠋꠋꠋꠋꠋꠋꠋꠋꠋꠋꠋꠋꠋꠋꠋꠋꠋꠋꠋ𑲭𑲭𑲭",
    "history": [
      "lanzstoreee"
    ]
  },
  "8198395643": {
    "name": "𝙰𝚁𝙺𝚉𝚉 𝙸𝚂 𝙳𝙴𝚅 | 𝙏𝙝𝙚 𝙆𝙞𝙣𝙜 👑",
    "history": []
  },
  "5997757720": {
    "name": "rieltzy #4tos.",
    "history": []
  },
  "7993507486": {
    "name": "minzy",
    "history": [
      "Minzy_Real"
    ]
  },
  "5871379389": {
    "name": "𝙼𝚊𝚢𝚣𝚣𝚇 𝑇5",
    "history": [
      "MayzzX"
    ]
  },
  "8290344956": {
    "name": "kelzzzofficial",
    "history": [
      "Kelzz67"
    ]
  },
  "8831298833": {
    "name": "𝒃𝒂𝒍𝒛 𝒇𝒐𝒓𝒕𝒘𝒚𝒏𝒕𝒚",
    "history": []
  },
  "6500116253": {
    "name": "Rènn",
    "history": []
  },
  "8728911549": {
    "name": "riffat",
    "history": []
  },
  "8343862244": {
    "name": "yes i,m",
    "history": []
  },
  "8787071976": {
    "name": "RICO",
    "history": []
  },
  "8515010894": {
    "name": "ANTI LINK GB CH",
    "history": [
      "dilarangmelarangbot"
    ]
  },
  "7824453416": {
    "name": "⸸ 𝒙𝒗𝒂𝒏̌𝒆𝒔𝒄𝒕 𝒚𝒖𝒄𝒂𝒏𝒏",
    "history": []
  },
  "7266650110": {
    "name": "NISS #𝚇𝚂𝚂",
    "history": [
      "Danz123br"
    ]
  },
  "8988645323": {
    "name": "𝙇𝙀𝙊 𝙊𝙁𝙁𝙄𝘾𝙄𝘼𝙇!",
    "history": []
  },
  "8075643350": {
    "name": "⌕ 𝐃𝐚𝐩𝐚𝐚𝐱𝐬 | 𝐍𝐇",
    "history": []
  },
  "8672317538": {
    "name": "[PR!NCE_DANZX 𝐓𝟓]§",
    "history": []
  },
  "8980561689": {
    "name": "Langznyabobo 𝐍𝟏",
    "history": [
      "g1l4ngajaa"
    ]
  },
  "6830127715": {
    "name": "Takashi #4Tos",
    "history": [
      "TakashiSukaTete"
    ]
  },
  "8171712431": {
    "name": "dimz [ REAL DEV SARXFORZ ]",
    "history": []
  },
  "8788287625": {
    "name": "クラン YASZX OFFICIAL",
    "history": []
  },
  "8832733318": {
    "name": "Wanzie",
    "history": []
  },
  "8565544067": {
    "name": "𝐒𖥕𝐂𝐔𝐑𝐈𝐓𝐘 卐 𝐃𖥕𝐌𝐈𝐍𝐈𝐂",
    "history": [
      "FloryMultiDevice_bot"
    ]
  },
  "8719325857": {
    "name": "BOT BUILD APK",
    "history": [
      "Web2apknew_bot"
    ]
  },
  "8619914419": {
    "name": "Rin",
    "history": []
  },
  "8080056323": {
    "name": "AKUN PROMOSI",
    "history": [
      "accountseccond"
    ]
  },
  "8749263861": {
    "name": "Frankus",
    "history": [
      "XPZORJ"
    ]
  },
  "8624358264": {
    "name": "MASS JUMAVO",
    "history": []
  },
  "8690522889": {
    "name": "𝕹𝖊𝖜𝕰𝖗𝖆 [𝗔𝟳𝟲] 𝗔𝗵𝘀𝗮𝗻 §§§|§§§",
    "history": []
  },
  "8757429524": {
    "name": "ᴠɪɴᴢᴢʜᴏsᴛ",
    "history": []
  },
  "8480499255": {
    "name": "AKU",
    "history": [
      "cacacanteq69"
    ]
  },
  "8536149501": {
    "name": "BOT RESELLER",
    "history": [
      "BotTirzz_bot"
    ]
  },
  "7378825277": {
    "name": "REKAP BOT FREEMIUM",
    "history": [
      "botrkpfree_bot"
    ]
  },
  "8530552266": {
    "name": "ρanσ",
    "history": [
      "asha2l"
    ]
  },
  "8684462348": {
    "name": "Devan",
    "history": []
  },
  "7756420202": {
    "name": "nzrl",
    "history": [
      "mnazrilxchito"
    ]
  },
  "8825166918": {
    "name": "Fahrixor",
    "history": []
  },
  "8867594398": {
    "name": "samz",
    "history": []
  },
  "8689855815": {
    "name": "𝐅𝐀𝐋𝐙 𝐓𝟓",
    "history": [
      "rowr011"
    ]
  },
  "8048764825": {
    "name": "𝐑𝐘𝐔𝐔 𝐓𝟓",
    "history": []
  },
  "8786210868": {
    "name": "𝕷𝖊𝖛𝖎乂𝖀𝖓𝖎",
    "history": []
  },
  "8874562580": {
    "name": "P",
    "history": [
      "Misterianjes"
    ]
  },
  "8609770617": {
    "name": "tׁׅɑׁׅׅ꯱ᨮׁׅ֮ɑׁׅɑׁׅ",
    "history": []
  },
  "7769799791": {
    "name": "⋆ 𝐑𝐄𝐀𝐋 𝐙𝐘𝐐𝐗𝐙 𝐓𝟓!",
    "history": []
  },
  "8392671313": {
    "name": "𝐄𝐕𝐑 | PARO #immortal.ん #executive | 𝐓𝟓🥇",
    "history": [
      "Imortalhaters"
    ]
  },
  "4349141105": {
    "name": "",
    "history": [
      "yatiemmn"
    ]
  },
  "8322071816": {
    "name": "rokzy",
    "history": []
  },
  "8685933117": {
    "name": "𝗥𝘆𝘂𝘂 𝗫𝘃𝗹𝗼𝗶𝘅",
    "history": []
  },
  "8488114208": {
    "name": "Darkness",
    "history": []
  },
  "7965989422": {
    "name": "yg baca",
    "history": []
  },
  "8287675614": {
    "name": "Sam_Cuwekk",
    "history": [
      "sam_cuwekk"
    ]
  },
  "8642241108": {
    "name": "乂 𝑶𝒎 [𝗔𝟳𝟲] 乂",
    "history": [
      "abityzreall"
    ]
  },
  "7504765830": {
    "name": "Support Monzo Banking Service",
    "history": [
      "Officiall_Monzo_Banking"
    ]
  },
  "7748558184": {
    "name": "—Asta",
    "history": []
  },
  "5394608537": {
    "name": "Chael",
    "history": []
  },
  "8312899793": {
    "name": "𝚖𝚢 𝚕𝚒𝚝𝚝𝚕𝚎 𝚋𝚘𝚕𝚞 𝚔𝚎𝚝𝚊𝚗 #𝐒𝐥𝐒 ཀ",
    "history": []
  },
  "7573695949": {
    "name": "ⓘ Monnnarrrc 🏅",
    "history": []
  },
  "8432945113": {
    "name": "FryDie",
    "history": []
  },
  "8510355954": {
    "name": "Support CoinMarketCap Service",
    "history": [
      "CoinMarketCap_Official_Service44"
    ]
  }
}